MANIFEST.in
requirements-test.txt
requirements.txt
setup.cfg
setup.py
dli/__init__.py
dli/cli/__init__.py
dli/cli/boto_authenticator.py
dli/cli/command_line.py
dli/client/__init__.py
dli/client/builders.py
dli/client/dli_client.py
dli/client/logging.py
dli/client/session.py
dli/components/__init__.py
dli/components/auto_reg_metadata.py
dli/components/datafile.py
dli/components/dataset.py
dli/components/dictionary.py
dli/components/package.py
dli/gui/__init__.py
dli/models/__init__.py
dli/models/dataset_factory.py
dli/models/dataset_model.py
dli/models/dictionary_model.py
dli/models/file_model.py
dli/models/instance_model.py
dli/models/instance_model_collection.py
dli/models/package_model.py
dli/models/sample_data_model.py
dli/models/structured_dataset_model.py
dli/models/unstructured_dataset_model.py
dli/modules/__init__.py
dli/modules/dataset_module.py
dli/modules/package_module.py
platform_services_lib/.dockerignore
platform_services_lib/.gitignore
platform_services_lib/.gitlab-ci.yml
platform_services_lib/README.md
platform_services_lib/__init__.py
platform_services_lib/requirements.txt
platform_services_lib/setup.cfg
platform_services_lib/setup.py
platform_services_lib/__pycache__/__init__.cpython-37.pyc
platform_services_lib/_dev-setup/docker/ecr_login.sh
platform_services_lib/_dev-setup/docker/octo_latest_linux_amd64/CHANGELOG.md
platform_services_lib/_dev-setup/docker/octo_latest_linux_amd64/LICENSE
platform_services_lib/_dev-setup/docker/octo_latest_linux_amd64/README.md
platform_services_lib/_dev-setup/docker/octo_latest_linux_amd64/octo
platform_services_lib/_dev-setup/docker/octo_latest_linux_amd64/octo_latest_linux_amd64.zip
platform_services_lib/_dev-setup/docker/octo_latest_mac_x86_64/README
platform_services_lib/_dev-setup/docker/octo_latest_mac_x86_64/octo
platform_services_lib/lib/__init__.py
platform_services_lib/lib/logging.py
platform_services_lib/lib/__pycache__/__init__.cpython-37.pyc
platform_services_lib/lib/adapters/__init__.py
