Metadata-Version: 2.1
Name: dli
Version: 1.19.0
Summary: Data Lake command line Interface.
Home-page: https://ihsmarkit.com
Author: IHS Markit Data Lake Team
Author-email: IHSM-datalake-support@ihsmarkit.com
License: MOZ-2
Keywords: cli,datalake,data,lake
Platform: UNKNOWN
Classifier: Intended Audience :: Developers
Classifier: Topic :: Software Development :: Libraries :: Python Modules
Classifier: License :: OSI Approved :: Mozilla Public License 2.0 (MPL 2.0)
Classifier: Natural Language :: English
Classifier: Operating System :: OS Independent
Classifier: Programming Language :: Python :: 3
Classifier: Programming Language :: Python :: 3.6
Requires-Python: >3.6.0
Provides-Extra: dask
Provides-Extra: ipython
